gutenberg/__init__.py
gutenberg/_domain_model/__init__.py
gutenberg/_domain_model/exceptions.py
gutenberg/_domain_model/persistence.py
gutenberg/_domain_model/text.py
gutenberg/_domain_model/types.py
gutenberg/_domain_model/vocabulary.py
gutenberg/_util/__init__.py
gutenberg/_util/abc.py
gutenberg/_util/logging.py
gutenberg/_util/objects.py
gutenberg/_util/os.py
gutenberg/_util/url.py
gutenberg/acquire/__init__.py
gutenberg/acquire/metadata.py
gutenberg/acquire/text.py
gutenberg/cleanup/__init__.py
gutenberg/cleanup/strip_headers.py
gutenberg/query/__init__.py
gutenberg/query/api.py
gutenberg/query/extractors.py
Gutenberg-0.8.2.dist-info/LICENSE.txt
Gutenberg-0.8.2.dist-info/METADATA
Gutenberg-0.8.2.dist-info/WHEEL
Gutenberg-0.8.2.dist-info/top_level.txt
Gutenberg-0.8.2.dist-info/RECORD
