Metadata-Version: 2.1
Name: Gutenberg
Version: 0.8.2
Summary: Library to interface with Project Gutenberg
Home-page: https://github.com/c-w/Gutenberg
Author: Clemens Wolff
Author-email: clemens.wolff+pypi@gmail.com
License: Apache Software License
Download-URL: https://pypi.python.org/pypi/Gutenberg
Platform: UNKNOWN
Classifier: Development Status :: 5 - Production/Stable
Classifier: License :: OSI Approved :: Apache Software License
Classifier: Programming Language :: Python :: 2
Classifier: Programming Language :: Python :: 2.7
Classifier: Programming Language :: Python :: 3
Classifier: Programming Language :: Python :: 3.6
Classifier: Programming Language :: Python :: 3.7
Classifier: Programming Language :: Python :: 3.8
Classifier: Programming Language :: Python :: 3.9
Classifier: Topic :: Utilities
Requires-Python: >=2.7.*,!=3.0.*,!=3.1.*,!=3.2.*,!=3.3.*,!=3.4.*
License-File: LICENSE.txt
Requires-Dist: SPARQLWrapper (>=1.8.2)
Requires-Dist: bsddb3 (>=6.1.0)
Requires-Dist: future (>=0.15.2)
Requires-Dist: pyparsing (<3.0.0)
Requires-Dist: rdflib-sqlalchemy (>=0.3.8)
Requires-Dist: rdflib (<5.0.0,>=4.2.0)
Requires-Dist: requests (>=2.5.1)
Requires-Dist: setuptools (>=18.5)
Requires-Dist: six (>=1.10.0)
